brownfox.py
setup.py
brownfox.egg-info/PKG-INFO
brownfox.egg-info/SOURCES.txt
brownfox.egg-info/dependency_links.txt
brownfox.egg-info/entry_points.txt
brownfox.egg-info/top_level.txt