Metadata-Version: 1.1
Name: brownfox
Version: 0.1.1
Summary: The quick brown fox switches directories amazingly fast
Home-page: UNKNOWN
Author: introom
Author-email: i@introo.me
License: UNKNOWN
Keywords: shell bookmark directory
Platform: UNKNOWN
Classifier: Topic :: Terminals
